{
	"name": "MinePuzzleWorld",
	"events": [
		{
			"eventType": "variable",
			"name": "HP",
			"type": "number",
			"initialValue": "3",
			"comment": "",
			"isStatic": false,
			"isConstant": false,
			"sid": 159484642559131
		},
		{
			"eventType": "variable",
			"name": "MineLevelComp",
			"type": "boolean",
			"initialValue": "false",
			"comment": "",
			"isStatic": false,
			"isConstant": false,
			"sid": 227647604735636
		},
		{
			"eventType": "block",
			"conditions": [
				{
					"id": "key-is-down",
					"objectClass": "key",
					"sid": 559707062624547,
					"parameters": {
						"key": 39
					},
					"isInverted": true
				},
				{
					"id": "key-is-down",
					"objectClass": "key",
					"sid": 622325583229778,
					"parameters": {
						"key": 38
					},
					"isInverted": true
				},
				{
					"id": "key-is-down",
					"objectClass": "key",
					"sid": 898039319361252,
					"parameters": {
						"key": 40
					},
					"isInverted": true
				},
				{
					"id": "key-is-down",
					"objectClass": "key",
					"sid": 583903086912997,
					"parameters": {
						"key": 37
					},
					"isInverted": true
				},
				{
					"id": "compare-boolean-eventvar",
					"objectClass": "System",
					"sid": 898089520532596,
					"parameters": {
						"variable": "Walking"
					}
				}
			],
			"actions": [
				{
					"id": "set-animation",
					"objectClass": "TestPlayerC",
					"sid": 248213711392189,
					"parameters": {
						"animation": "\"Idle\"",
						"from": "beginning"
					}
				},
				{
					"id": "set-animation",
					"objectClass": "PlayerShadow",
					"sid": 297381121618651,
					"parameters": {
						"animation": "\"IDLE\"",
						"from": "beginning"
					}
				},
				{
					"id": "set-boolean-eventvar",
					"objectClass": "System",
					"sid": 792824697242970,
					"parameters": {
						"variable": "Walking",
						"value": "false"
					}
				}
			],
			"sid": 516650374637985
		},
		{
			"eventType": "block",
			"conditions": [
				{
					"id": "key-is-down",
					"objectClass": "key",
					"sid": 645475142427683,
					"parameters": {
						"key": 39
					}
				}
			],
			"actions": [
				{
					"id": "set-animation",
					"objectClass": "TestPlayerC",
					"sid": 751128565329154,
					"parameters": {
						"animation": "\"Walk\"",
						"from": "beginning"
					}
				},
				{
					"id": "set-animation",
					"objectClass": "PlayerShadow",
					"sid": 514724645376823,
					"parameters": {
						"animation": "\"Walk\"",
						"from": "beginning"
					}
				},
				{
					"id": "set-boolean-eventvar",
					"objectClass": "System",
					"sid": 917049307351518,
					"parameters": {
						"variable": "Walking",
						"value": "true"
					}
				},
				{
					"id": "set-mirrored",
					"objectClass": "TestPlayerC",
					"sid": 896326154507208,
					"parameters": {
						"state": "not-mirrored"
					}
				},
				{
					"id": "set-boolean-eventvar",
					"objectClass": "System",
					"sid": 734966162909335,
					"parameters": {
						"variable": "LeftORRight",
						"value": "false"
					}
				}
			],
			"sid": 341118276450792
		},
		{
			"eventType": "block",
			"conditions": [
				{
					"id": "key-is-down",
					"objectClass": "key",
					"sid": 864251258388743,
					"parameters": {
						"key": 37
					}
				}
			],
			"actions": [
				{
					"id": "set-animation",
					"objectClass": "TestPlayerC",
					"sid": 183057839181248,
					"parameters": {
						"animation": "\"Walk\"",
						"from": "beginning"
					}
				},
				{
					"id": "set-animation",
					"objectClass": "PlayerShadow",
					"sid": 515272448212306,
					"parameters": {
						"animation": "\"Walk\"",
						"from": "beginning"
					}
				},
				{
					"id": "set-boolean-eventvar",
					"objectClass": "System",
					"sid": 321113763299571,
					"parameters": {
						"variable": "Walking",
						"value": "true"
					}
				},
				{
					"id": "set-mirrored",
					"objectClass": "TestPlayerC",
					"sid": 807600392330863,
					"parameters": {
						"state": "mirrored"
					}
				},
				{
					"id": "set-boolean-eventvar",
					"objectClass": "System",
					"sid": 500314772564816,
					"parameters": {
						"variable": "LeftORRight",
						"value": "true"
					}
				}
			],
			"sid": 241781105439162
		},
		{
			"eventType": "block",
			"conditions": [
				{
					"id": "key-is-down",
					"objectClass": "key",
					"sid": 872023712153831,
					"parameters": {
						"key": 38
					}
				}
			],
			"actions": [
				{
					"id": "set-animation",
					"objectClass": "TestPlayerC",
					"sid": 608434257221868,
					"parameters": {
						"animation": "\"Walk\"",
						"from": "beginning"
					}
				},
				{
					"id": "set-animation",
					"objectClass": "PlayerShadow",
					"sid": 450825836892654,
					"parameters": {
						"animation": "\"Walk\"",
						"from": "beginning"
					}
				},
				{
					"id": "set-boolean-eventvar",
					"objectClass": "System",
					"sid": 801995044719528,
					"parameters": {
						"variable": "Walking",
						"value": "true"
					}
				},
				{
					"id": "set-mirrored",
					"objectClass": "TestPlayerC",
					"sid": 125253218013331,
					"parameters": {
						"state": "not-mirrored"
					}
				}
			],
			"sid": 285294932439855
		},
		{
			"eventType": "block",
			"conditions": [
				{
					"id": "key-is-down",
					"objectClass": "key",
					"sid": 217125157400964,
					"parameters": {
						"key": 40
					}
				},
				{
					"id": "compare-boolean-eventvar",
					"objectClass": "System",
					"sid": 934653169513576,
					"parameters": {
						"variable": "LeftORRight"
					}
				}
			],
			"actions": [
				{
					"id": "set-animation",
					"objectClass": "TestPlayerC",
					"sid": 658368018647057,
					"parameters": {
						"animation": "\"Walk\"",
						"from": "beginning"
					}
				},
				{
					"id": "set-animation",
					"objectClass": "PlayerShadow",
					"sid": 244909205610810,
					"parameters": {
						"animation": "\"Walk\"",
						"from": "beginning"
					}
				},
				{
					"id": "set-mirrored",
					"objectClass": "TestPlayerC",
					"sid": 396220801935437,
					"parameters": {
						"state": "mirrored"
					}
				},
				{
					"id": "set-boolean-eventvar",
					"objectClass": "System",
					"sid": 340388878560932,
					"parameters": {
						"variable": "Walking",
						"value": "true"
					}
				}
			],
			"sid": 698373191662041
		},
		{
			"eventType": "block",
			"conditions": [
				{
					"id": "key-is-down",
					"objectClass": "key",
					"sid": 534356786338170,
					"parameters": {
						"key": 40
					}
				},
				{
					"id": "compare-boolean-eventvar",
					"objectClass": "System",
					"sid": 163961254501972,
					"parameters": {
						"variable": "LeftORRight"
					},
					"isInverted": true
				}
			],
			"actions": [
				{
					"id": "set-animation",
					"objectClass": "TestPlayerC",
					"sid": 703742489441107,
					"parameters": {
						"animation": "\"Walk\"",
						"from": "beginning"
					}
				},
				{
					"id": "set-animation",
					"objectClass": "PlayerShadow",
					"sid": 366402121996501,
					"parameters": {
						"animation": "\"Walk\"",
						"from": "beginning"
					}
				},
				{
					"id": "set-boolean-eventvar",
					"objectClass": "System",
					"sid": 563726481610794,
					"parameters": {
						"variable": "Walking",
						"value": "true"
					}
				},
				{
					"id": "set-mirrored",
					"objectClass": "TestPlayerC",
					"sid": 329192227903108,
					"parameters": {
						"state": "not-mirrored"
					}
				}
			],
			"sid": 645484064298748
		},
		{
			"eventType": "block",
			"conditions": [
				{
					"id": "on-collision-with-another-object",
					"objectClass": "TestPlayerC",
					"sid": 143545623364924,
					"parameters": {
						"object": "MineTrack1"
					}
				}
			],
			"actions": [
				{
					"id": "stop",
					"objectClass": "TestPlayerC",
					"sid": 951725837737768,
					"behaviorType": "8Direction"
				},
				{
					"id": "set-enabled",
					"objectClass": "TestPlayerC",
					"sid": 224786395957467,
					"behaviorType": "8Direction",
					"parameters": {
						"state": "disabled"
					}
				},
				{
					"id": "set-enabled",
					"objectClass": "TestPlayerC",
					"sid": 108313955749544,
					"behaviorType": "ScrollTo",
					"parameters": {
						"state": "disabled"
					}
				},
				{
					"id": "set-visible",
					"objectClass": "TestPlayerC",
					"sid": 680176913878903,
					"parameters": {
						"visibility": "invisible"
					}
				},
				{
					"id": "set-position",
					"objectClass": "TestPlayerC",
					"sid": 927653079823365,
					"parameters": {
						"x": "MineTrack1B2.X",
						"y": "MineTrack1B2.Y"
					}
				},
				{
					"id": "set-visible",
					"objectClass": "MineCartWall",
					"sid": 294040020929398,
					"parameters": {
						"visibility": "visible"
					}
				},
				{
					"id": "set-visible",
					"objectClass": "MCCartl",
					"sid": 717955764004285,
					"parameters": {
						"visibility": "visible"
					}
				},
				{
					"id": "set-enabled",
					"objectClass": "MCCartl",
					"sid": 551754837682312,
					"behaviorType": "ScrollTo",
					"parameters": {
						"state": "enabled"
					}
				},
				{
					"id": "play-timeline",
					"objectClass": "TimelineController",
					"sid": 686495090498502,
					"parameters": {
						"timeline": "Timeline 1",
						"tags": "\"Cart\""
					}
				},
				{
					"id": "wait",
					"objectClass": "System",
					"sid": 863059471192742,
					"parameters": {
						"seconds": "3"
					}
				},
				{
					"id": "stop-timeline-by-tags",
					"objectClass": "TimelineController",
					"sid": 280013669029572,
					"parameters": {
						"tags": "\"Cart\""
					}
				},
				{
					"id": "set-enabled",
					"objectClass": "MCCartl",
					"sid": 214491988975562,
					"behaviorType": "ScrollTo",
					"parameters": {
						"state": "disabled"
					}
				},
				{
					"id": "set-visible",
					"objectClass": "MineCartWall",
					"sid": 444291109112678,
					"parameters": {
						"visibility": "invisible"
					}
				},
				{
					"id": "set-visible",
					"objectClass": "MCCartl",
					"sid": 837582318886800,
					"parameters": {
						"visibility": "invisible"
					}
				},
				{
					"id": "set-visible",
					"objectClass": "TestPlayerC",
					"sid": 984779262146813,
					"parameters": {
						"visibility": "visible"
					}
				},
				{
					"id": "set-enabled",
					"objectClass": "TestPlayerC",
					"sid": 244179440595997,
					"behaviorType": "ScrollTo",
					"parameters": {
						"state": "enabled"
					}
				},
				{
					"id": "set-enabled",
					"objectClass": "TestPlayerC",
					"sid": 731572580522628,
					"behaviorType": "8Direction",
					"parameters": {
						"state": "enabled"
					}
				}
			],
			"sid": 465504055331326
		},
		{
			"eventType": "block",
			"conditions": [
				{
					"id": "on-collision-with-another-object",
					"objectClass": "TestPlayerC",
					"sid": 456692760669932,
					"parameters": {
						"object": "MineTrack1B"
					}
				}
			],
			"actions": [
				{
					"id": "stop",
					"objectClass": "TestPlayerC",
					"sid": 776416860012839,
					"behaviorType": "8Direction"
				},
				{
					"id": "set-enabled",
					"objectClass": "TestPlayerC",
					"sid": 841456328100004,
					"behaviorType": "8Direction",
					"parameters": {
						"state": "disabled"
					}
				},
				{
					"id": "set-enabled",
					"objectClass": "TestPlayerC",
					"sid": 811574583982068,
					"behaviorType": "ScrollTo",
					"parameters": {
						"state": "disabled"
					}
				},
				{
					"id": "set-visible",
					"objectClass": "TestPlayerC",
					"sid": 823722626147020,
					"parameters": {
						"visibility": "invisible"
					}
				},
				{
					"id": "set-position",
					"objectClass": "TestPlayerC",
					"sid": 218921859615526,
					"parameters": {
						"x": "MineTrack1A.X",
						"y": "MineTrack1A.Y"
					}
				},
				{
					"id": "set-visible",
					"objectClass": "MineCartWall",
					"sid": 426407830733452,
					"parameters": {
						"visibility": "visible"
					}
				},
				{
					"id": "set-visible",
					"objectClass": "MCCartl",
					"sid": 228656944026898,
					"parameters": {
						"visibility": "visible"
					}
				},
				{
					"id": "set-enabled",
					"objectClass": "MCCartl",
					"sid": 808630523143590,
					"behaviorType": "ScrollTo",
					"parameters": {
						"state": "enabled"
					}
				},
				{
					"id": "play-timeline",
					"objectClass": "TimelineController",
					"sid": 861718390952766,
					"parameters": {
						"timeline": "Timeline 1",
						"tags": "\"Cart\""
					}
				},
				{
					"id": "wait",
					"objectClass": "System",
					"sid": 747617819756643,
					"parameters": {
						"seconds": "3"
					}
				},
				{
					"id": "stop-timeline-by-tags",
					"objectClass": "TimelineController",
					"sid": 895204217666261,
					"parameters": {
						"tags": "\"Cart\""
					}
				},
				{
					"id": "set-enabled",
					"objectClass": "MCCartl",
					"sid": 563981534506194,
					"behaviorType": "ScrollTo",
					"parameters": {
						"state": "disabled"
					}
				},
				{
					"id": "set-visible",
					"objectClass": "MineCartWall",
					"sid": 229347546202785,
					"parameters": {
						"visibility": "invisible"
					}
				},
				{
					"id": "set-visible",
					"objectClass": "MCCartl",
					"sid": 144746368971080,
					"parameters": {
						"visibility": "invisible"
					}
				},
				{
					"id": "set-visible",
					"objectClass": "TestPlayerC",
					"sid": 436324826537960,
					"parameters": {
						"visibility": "visible"
					}
				},
				{
					"id": "set-enabled",
					"objectClass": "TestPlayerC",
					"sid": 370735127220869,
					"behaviorType": "ScrollTo",
					"parameters": {
						"state": "enabled"
					}
				},
				{
					"id": "set-enabled",
					"objectClass": "TestPlayerC",
					"sid": 402844777155040,
					"behaviorType": "8Direction",
					"parameters": {
						"state": "enabled"
					}
				}
			],
			"sid": 876865380865478
		},
		{
			"eventType": "block",
			"conditions": [
				{
					"id": "on-collision-with-another-object",
					"objectClass": "TestPlayerC",
					"sid": 730242828254285,
					"parameters": {
						"object": "MineTrack2"
					}
				}
			],
			"actions": [
				{
					"id": "stop",
					"objectClass": "TestPlayerC",
					"sid": 533745905968511,
					"behaviorType": "8Direction"
				},
				{
					"id": "set-enabled",
					"objectClass": "TestPlayerC",
					"sid": 582274494341857,
					"behaviorType": "8Direction",
					"parameters": {
						"state": "disabled"
					}
				},
				{
					"id": "set-enabled",
					"objectClass": "TestPlayerC",
					"sid": 703598985669815,
					"behaviorType": "ScrollTo",
					"parameters": {
						"state": "disabled"
					}
				},
				{
					"id": "set-visible",
					"objectClass": "TestPlayerC",
					"sid": 644452191515318,
					"parameters": {
						"visibility": "invisible"
					}
				},
				{
					"id": "set-position",
					"objectClass": "TestPlayerC",
					"sid": 211963970429914,
					"parameters": {
						"x": "MineTrack2B2.X",
						"y": "MineTrack2B2.Y"
					}
				},
				{
					"id": "set-visible",
					"objectClass": "MineCartWall",
					"sid": 272971689015410,
					"parameters": {
						"visibility": "visible"
					}
				},
				{
					"id": "set-visible",
					"objectClass": "MCCartl",
					"sid": 914270224000187,
					"parameters": {
						"visibility": "visible"
					}
				},
				{
					"id": "set-enabled",
					"objectClass": "MCCartl",
					"sid": 154297861511106,
					"behaviorType": "ScrollTo",
					"parameters": {
						"state": "enabled"
					}
				},
				{
					"id": "play-timeline",
					"objectClass": "TimelineController",
					"sid": 630959145752241,
					"parameters": {
						"timeline": "Timeline 1",
						"tags": "\"Cart\""
					}
				},
				{
					"id": "wait",
					"objectClass": "System",
					"sid": 151463296649403,
					"parameters": {
						"seconds": "3"
					}
				},
				{
					"id": "stop-timeline-by-tags",
					"objectClass": "TimelineController",
					"sid": 580031178515741,
					"parameters": {
						"tags": "\"Cart\""
					}
				},
				{
					"id": "set-enabled",
					"objectClass": "MCCartl",
					"sid": 610843052650838,
					"behaviorType": "ScrollTo",
					"parameters": {
						"state": "disabled"
					}
				},
				{
					"id": "set-visible",
					"objectClass": "MineCartWall",
					"sid": 302754963542534,
					"parameters": {
						"visibility": "invisible"
					}
				},
				{
					"id": "set-visible",
					"objectClass": "MCCartl",
					"sid": 825064100965119,
					"parameters": {
						"visibility": "invisible"
					}
				},
				{
					"id": "set-visible",
					"objectClass": "TestPlayerC",
					"sid": 976589129989735,
					"parameters": {
						"visibility": "visible"
					}
				},
				{
					"id": "set-enabled",
					"objectClass": "TestPlayerC",
					"sid": 348004176953117,
					"behaviorType": "ScrollTo",
					"parameters": {
						"state": "enabled"
					}
				},
				{
					"id": "set-enabled",
					"objectClass": "TestPlayerC",
					"sid": 220890775737425,
					"behaviorType": "8Direction",
					"parameters": {
						"state": "enabled"
					}
				}
			],
			"sid": 942483738970947
		},
		{
			"eventType": "block",
			"conditions": [
				{
					"id": "on-collision-with-another-object",
					"objectClass": "TestPlayerC",
					"sid": 216046063732563,
					"parameters": {
						"object": "MineTrack2B"
					}
				}
			],
			"actions": [
				{
					"id": "stop",
					"objectClass": "TestPlayerC",
					"sid": 481716675814693,
					"behaviorType": "8Direction"
				},
				{
					"id": "set-enabled",
					"objectClass": "TestPlayerC",
					"sid": 135724263902972,
					"behaviorType": "8Direction",
					"parameters": {
						"state": "disabled"
					}
				},
				{
					"id": "set-enabled",
					"objectClass": "TestPlayerC",
					"sid": 751980788137257,
					"behaviorType": "ScrollTo",
					"parameters": {
						"state": "disabled"
					}
				},
				{
					"id": "set-visible",
					"objectClass": "TestPlayerC",
					"sid": 437646451684072,
					"parameters": {
						"visibility": "invisible"
					}
				},
				{
					"id": "set-position",
					"objectClass": "TestPlayerC",
					"sid": 964369643356872,
					"parameters": {
						"x": "MineTrack2A.X",
						"y": "MineTrack2A.Y"
					}
				},
				{
					"id": "set-visible",
					"objectClass": "MineCartWall",
					"sid": 300801577026748,
					"parameters": {
						"visibility": "visible"
					}
				},
				{
					"id": "set-visible",
					"objectClass": "MCCartl",
					"sid": 806944923296726,
					"parameters": {
						"visibility": "visible"
					}
				},
				{
					"id": "set-enabled",
					"objectClass": "MCCartl",
					"sid": 566294222507624,
					"behaviorType": "ScrollTo",
					"parameters": {
						"state": "enabled"
					}
				},
				{
					"id": "play-timeline",
					"objectClass": "TimelineController",
					"sid": 479968971388510,
					"parameters": {
						"timeline": "Timeline 1",
						"tags": "\"Cart\""
					}
				},
				{
					"id": "wait",
					"objectClass": "System",
					"sid": 525658743150970,
					"parameters": {
						"seconds": "3"
					}
				},
				{
					"id": "stop-timeline-by-tags",
					"objectClass": "TimelineController",
					"sid": 230351176904649,
					"parameters": {
						"tags": "\"Cart\""
					}
				},
				{
					"id": "set-enabled",
					"objectClass": "MCCartl",
					"sid": 663055310142368,
					"behaviorType": "ScrollTo",
					"parameters": {
						"state": "disabled"
					}
				},
				{
					"id": "set-visible",
					"objectClass": "MineCartWall",
					"sid": 112828914665539,
					"parameters": {
						"visibility": "invisible"
					}
				},
				{
					"id": "set-visible",
					"objectClass": "MCCartl",
					"sid": 475678316549775,
					"parameters": {
						"visibility": "invisible"
					}
				},
				{
					"id": "set-visible",
					"objectClass": "TestPlayerC",
					"sid": 552446458564729,
					"parameters": {
						"visibility": "visible"
					}
				},
				{
					"id": "set-enabled",
					"objectClass": "TestPlayerC",
					"sid": 413839314587212,
					"behaviorType": "ScrollTo",
					"parameters": {
						"state": "enabled"
					}
				},
				{
					"id": "set-enabled",
					"objectClass": "TestPlayerC",
					"sid": 493256710041644,
					"behaviorType": "8Direction",
					"parameters": {
						"state": "enabled"
					}
				}
			],
			"sid": 731152980741197
		},
		{
			"eventType": "block",
			"conditions": [
				{
					"id": "on-collision-with-another-object",
					"objectClass": "TestPlayerC",
					"sid": 824134963451294,
					"parameters": {
						"object": "MineTrack3"
					}
				}
			],
			"actions": [
				{
					"id": "stop",
					"objectClass": "TestPlayerC",
					"sid": 307688103362218,
					"behaviorType": "8Direction"
				},
				{
					"id": "set-enabled",
					"objectClass": "TestPlayerC",
					"sid": 824619990712905,
					"behaviorType": "8Direction",
					"parameters": {
						"state": "disabled"
					}
				},
				{
					"id": "set-enabled",
					"objectClass": "TestPlayerC",
					"sid": 205750295569812,
					"behaviorType": "ScrollTo",
					"parameters": {
						"state": "disabled"
					}
				},
				{
					"id": "set-visible",
					"objectClass": "TestPlayerC",
					"sid": 409806007488838,
					"parameters": {
						"visibility": "invisible"
					}
				},
				{
					"id": "set-position",
					"objectClass": "TestPlayerC",
					"sid": 643604221086576,
					"parameters": {
						"x": "MineTrack3B2.X",
						"y": "MineTrack3B2.Y"
					}
				},
				{
					"id": "set-visible",
					"objectClass": "MineCartWall",
					"sid": 173569747550791,
					"parameters": {
						"visibility": "visible"
					}
				},
				{
					"id": "set-visible",
					"objectClass": "MCCartl",
					"sid": 993625085827983,
					"parameters": {
						"visibility": "visible"
					}
				},
				{
					"id": "set-enabled",
					"objectClass": "MCCartl",
					"sid": 617101028917260,
					"behaviorType": "ScrollTo",
					"parameters": {
						"state": "enabled"
					}
				},
				{
					"id": "play-timeline",
					"objectClass": "TimelineController",
					"sid": 802456000015849,
					"parameters": {
						"timeline": "Timeline 1",
						"tags": "\"Cart\""
					}
				},
				{
					"id": "wait",
					"objectClass": "System",
					"sid": 824352527531303,
					"parameters": {
						"seconds": "3"
					}
				},
				{
					"id": "stop-timeline-by-tags",
					"objectClass": "TimelineController",
					"sid": 576829926195863,
					"parameters": {
						"tags": "\"Cart\""
					}
				},
				{
					"id": "set-enabled",
					"objectClass": "MCCartl",
					"sid": 799053261288026,
					"behaviorType": "ScrollTo",
					"parameters": {
						"state": "disabled"
					}
				},
				{
					"id": "set-visible",
					"objectClass": "MineCartWall",
					"sid": 346312773787948,
					"parameters": {
						"visibility": "invisible"
					}
				},
				{
					"id": "set-visible",
					"objectClass": "MCCartl",
					"sid": 270989706992303,
					"parameters": {
						"visibility": "invisible"
					}
				},
				{
					"id": "set-visible",
					"objectClass": "TestPlayerC",
					"sid": 189272479664993,
					"parameters": {
						"visibility": "visible"
					}
				},
				{
					"id": "set-enabled",
					"objectClass": "TestPlayerC",
					"sid": 732833689305734,
					"behaviorType": "ScrollTo",
					"parameters": {
						"state": "enabled"
					}
				},
				{
					"id": "set-enabled",
					"objectClass": "TestPlayerC",
					"sid": 557331979432529,
					"behaviorType": "8Direction",
					"parameters": {
						"state": "enabled"
					}
				}
			],
			"sid": 663886649356902
		},
		{
			"eventType": "block",
			"conditions": [
				{
					"id": "on-collision-with-another-object",
					"objectClass": "TestPlayerC",
					"sid": 269307441771828,
					"parameters": {
						"object": "MineTrack3B"
					}
				}
			],
			"actions": [
				{
					"id": "stop",
					"objectClass": "TestPlayerC",
					"sid": 886597878236799,
					"behaviorType": "8Direction"
				},
				{
					"id": "set-enabled",
					"objectClass": "TestPlayerC",
					"sid": 990479540773954,
					"behaviorType": "8Direction",
					"parameters": {
						"state": "disabled"
					}
				},
				{
					"id": "set-enabled",
					"objectClass": "TestPlayerC",
					"sid": 648294650142392,
					"behaviorType": "ScrollTo",
					"parameters": {
						"state": "disabled"
					}
				},
				{
					"id": "set-visible",
					"objectClass": "TestPlayerC",
					"sid": 113856335150486,
					"parameters": {
						"visibility": "invisible"
					}
				},
				{
					"id": "set-position",
					"objectClass": "TestPlayerC",
					"sid": 352433012458027,
					"parameters": {
						"x": "MineTrack3A.X",
						"y": "MineTrack3A.Y"
					}
				},
				{
					"id": "set-visible",
					"objectClass": "MineCartWall",
					"sid": 283591636165406,
					"parameters": {
						"visibility": "visible"
					}
				},
				{
					"id": "set-visible",
					"objectClass": "MCCartl",
					"sid": 623228646045720,
					"parameters": {
						"visibility": "visible"
					}
				},
				{
					"id": "set-enabled",
					"objectClass": "MCCartl",
					"sid": 871568514965830,
					"behaviorType": "ScrollTo",
					"parameters": {
						"state": "enabled"
					}
				},
				{
					"id": "play-timeline",
					"objectClass": "TimelineController",
					"sid": 268477642744148,
					"parameters": {
						"timeline": "Timeline 1",
						"tags": "\"Cart\""
					}
				},
				{
					"id": "wait",
					"objectClass": "System",
					"sid": 442124681815405,
					"parameters": {
						"seconds": "3"
					}
				},
				{
					"id": "stop-timeline-by-tags",
					"objectClass": "TimelineController",
					"sid": 483135898703570,
					"parameters": {
						"tags": "\"Cart\""
					}
				},
				{
					"id": "set-enabled",
					"objectClass": "MCCartl",
					"sid": 402841807642370,
					"behaviorType": "ScrollTo",
					"parameters": {
						"state": "disabled"
					}
				},
				{
					"id": "set-visible",
					"objectClass": "MineCartWall",
					"sid": 808151148749523,
					"parameters": {
						"visibility": "invisible"
					}
				},
				{
					"id": "set-visible",
					"objectClass": "MCCartl",
					"sid": 947857178102113,
					"parameters": {
						"visibility": "invisible"
					}
				},
				{
					"id": "set-visible",
					"objectClass": "TestPlayerC",
					"sid": 164556940732264,
					"parameters": {
						"visibility": "visible"
					}
				},
				{
					"id": "set-enabled",
					"objectClass": "TestPlayerC",
					"sid": 710439587246292,
					"behaviorType": "ScrollTo",
					"parameters": {
						"state": "enabled"
					}
				},
				{
					"id": "set-enabled",
					"objectClass": "TestPlayerC",
					"sid": 554817451839163,
					"behaviorType": "8Direction",
					"parameters": {
						"state": "enabled"
					}
				}
			],
			"sid": 154478456293178
		},
		{
			"eventType": "block",
			"conditions": [
				{
					"id": "every-tick",
					"objectClass": "System",
					"sid": 978858091681736
				}
			],
			"actions": [
				{
					"id": "pin-to-object-imagepoint",
					"objectClass": "PlayerShadow",
					"sid": 248380011013503,
					"behaviorType": "Pin",
					"parameters": {
						"pin-to": "TestPlayerC",
						"image-point": "0",
						"angle": false,
						"width-type": "no",
						"height-type": "no",
						"z": false
					}
				}
			],
			"sid": 409781664619984
		},
		{
			"eventType": "group",
			"disabled": false,
			"title": " Chase Ai Script2",
			"description": "",
			"isActiveOnStart": true,
			"children": [
				{
					"eventType": "block",
					"conditions": [
						{
							"id": "on-start-of-layout",
							"objectClass": "System",
							"sid": 190267737052121
						}
					],
					"actions": [
						{
							"id": "find-path",
							"objectClass": "chaseEnemy",
							"sid": 803439715349962,
							"behaviorType": "Pathfinding",
							"parameters": {
								"x": "chaseEnemy.X+random(-32, 32)",
								"y": "chaseEnemy.Y+random(-32, 32)"
							}
						},
						{
							"id": "set-animation",
							"objectClass": "chaseEnemy",
							"sid": 418930155702379,
							"parameters": {
								"animation": "\"IDLE\"",
								"from": "beginning"
							}
						}
					],
					"sid": 962985637206843
				},
				{
					"eventType": "block",
					"conditions": [
						{
							"id": "on-path-found",
							"objectClass": "chaseEnemy",
							"sid": 443204061959384,
							"behaviorType": "Pathfinding"
						}
					],
					"actions": [
						{
							"id": "move-along-path",
							"objectClass": "chaseEnemy",
							"sid": 631224249605044,
							"behaviorType": "Pathfinding"
						}
					],
					"sid": 976186820699328
				},
				{
					"eventType": "block",
					"conditions": [
						{
							"id": "on-failed-to-find-path",
							"objectClass": "chaseEnemy",
							"sid": 295344209798771,
							"behaviorType": "Pathfinding"
						}
					],
					"actions": [
						{
							"id": "find-path",
							"objectClass": "chaseEnemy",
							"sid": 596056323695124,
							"behaviorType": "Pathfinding",
							"parameters": {
								"x": "chaseEnemy.X+random(-32, 32)",
								"y": "chaseEnemy.Y+random(-32, 32)"
							}
						}
					],
					"sid": 198762117920948
				},
				{
					"eventType": "block",
					"conditions": [
						{
							"id": "has-los-to-object",
							"objectClass": "chaseEnemy",
							"sid": 794100796801795,
							"behaviorType": "LineOfSight",
							"parameters": {
								"object": "TestPlayerC",
								"image-point": "0"
							}
						}
					],
					"actions": [
						{
							"id": "set-animation",
							"objectClass": "chaseEnemy",
							"sid": 732294149713485,
							"parameters": {
								"animation": "\"HATE\"",
								"from": "beginning"
							}
						},
						{
							"id": "set-enabled",
							"objectClass": "chaseEnemy",
							"sid": 537895488604214,
							"behaviorType": "Pathfinding",
							"parameters": {
								"set": "disabled"
							}
						},
						{
							"id": "move-to-object",
							"objectClass": "chaseEnemy",
							"sid": 388620792056103,
							"behaviorType": "MoveTo",
							"parameters": {
								"object": "TestPlayerC",
								"image-point": "0",
								"mode": "direct"
							}
						},
						{
							"id": "wait",
							"objectClass": "System",
							"sid": 690797678304558,
							"disabled": true,
							"parameters": {
								"seconds": "2"
							}
						}
					],
					"sid": 712836508356597
				},
				{
					"eventType": "block",
					"conditions": [
						{
							"id": "has-los-to-object",
							"objectClass": "chaseEnemy",
							"sid": 246168953751677,
							"behaviorType": "LineOfSight",
							"parameters": {
								"object": "TestPlayerC",
								"image-point": "0"
							},
							"isInverted": true
						}
					],
					"actions": [
						{
							"id": "wait",
							"objectClass": "System",
							"sid": 756838268192657,
							"parameters": {
								"seconds": "2"
							}
						},
						{
							"id": "set-animation",
							"objectClass": "chaseEnemy",
							"sid": 275924387658878,
							"parameters": {
								"animation": "\"IDLE\"",
								"from": "beginning"
							}
						},
						{
							"id": "stop",
							"objectClass": "chaseEnemy",
							"sid": 209751523496226,
							"behaviorType": "MoveTo"
						}
					],
					"sid": 584947493439280,
					"children": [
						{
							"eventType": "block",
							"conditions": [
								{
									"id": "every-x-seconds",
									"objectClass": "System",
									"sid": 418021127115792,
									"parameters": {
										"interval-seconds": "random(3,6)"
									}
								}
							],
							"actions": [
								{
									"id": "find-path",
									"objectClass": "chaseEnemy",
									"sid": 644737165506436,
									"behaviorType": "Pathfinding",
									"parameters": {
										"x": "chaseEnemy.X+random(-32, 32)",
										"y": "chaseEnemy.Y+random(-32, 32)"
									}
								},
								{
									"id": "set-enabled",
									"objectClass": "chaseEnemy",
									"sid": 125498733279175,
									"behaviorType": "Pathfinding",
									"parameters": {
										"set": "enabled"
									}
								}
							],
							"sid": 101767237152645
						}
					]
				},
				{
					"eventType": "block",
					"conditions": [
						{
							"id": "on-collision-with-another-object",
							"objectClass": "chaseEnemy",
							"sid": 877870155232824,
							"parameters": {
								"object": "TestPlayerC"
							}
						}
					],
					"actions": [
						{
							"id": "subtract-from-eventvar",
							"objectClass": "System",
							"sid": 760304219031936,
							"parameters": {
								"variable": "HP",
								"value": "1"
							}
						},
						{
							"id": "flash",
							"objectClass": "TestPlayerC",
							"sid": 343216872347221,
							"behaviorType": "Flash",
							"parameters": {
								"on-time": "0.1",
								"off-time": "0.1",
								"duration": "1.0"
							}
						},
						{
							"id": "stop",
							"objectClass": "chaseEnemy",
							"sid": 356740761199489,
							"behaviorType": "MoveTo"
						},
						{
							"id": "wait",
							"objectClass": "System",
							"sid": 600758796705747,
							"parameters": {
								"seconds": "2"
							}
						}
					],
					"sid": 312001790774282
				},
				{
					"eventType": "block",
					"conditions": [
						{
							"id": "on-collision-with-another-object",
							"objectClass": "chaseEnemy",
							"sid": 423410477119455,
							"parameters": {
								"object": "TestPlayerC"
							}
						},
						{
							"id": "compare-eventvar",
							"objectClass": "System",
							"sid": 863863414050054,
							"parameters": {
								"variable": "HP",
								"comparison": 3,
								"value": "0"
							}
						}
					],
					"actions": [
						{
							"id": "restart-layout",
							"objectClass": "System",
							"sid": 568627150271176
						}
					],
					"sid": 462038855013313
				}
			],
			"sid": 991118947228592
		},
		{
			"eventType": "group",
			"disabled": false,
			"title": " Chase Ai Script3",
			"description": "",
			"isActiveOnStart": true,
			"children": [
				{
					"eventType": "block",
					"conditions": [
						{
							"id": "on-start-of-layout",
							"objectClass": "System",
							"sid": 775324537778098
						}
					],
					"actions": [
						{
							"id": "find-path",
							"objectClass": "chaseEnemy2",
							"sid": 632408140724353,
							"behaviorType": "Pathfinding",
							"parameters": {
								"x": "chaseEnemy2.X+random(-32, 32)",
								"y": "chaseEnemy2.Y+random(-32, 32)"
							}
						},
						{
							"id": "set-animation",
							"objectClass": "chaseEnemy2",
							"sid": 296159133922540,
							"parameters": {
								"animation": "\"IDLE\"",
								"from": "beginning"
							}
						}
					],
					"sid": 876512091095937
				},
				{
					"eventType": "block",
					"conditions": [
						{
							"id": "on-path-found",
							"objectClass": "chaseEnemy2",
							"sid": 343100441717830,
							"behaviorType": "Pathfinding"
						}
					],
					"actions": [
						{
							"id": "move-along-path",
							"objectClass": "chaseEnemy2",
							"sid": 342055256470154,
							"behaviorType": "Pathfinding"
						}
					],
					"sid": 671947705451703
				},
				{
					"eventType": "block",
					"conditions": [
						{
							"id": "on-failed-to-find-path",
							"objectClass": "chaseEnemy2",
							"sid": 779810177929232,
							"behaviorType": "Pathfinding"
						}
					],
					"actions": [
						{
							"id": "find-path",
							"objectClass": "chaseEnemy2",
							"sid": 587468702318391,
							"behaviorType": "Pathfinding",
							"parameters": {
								"x": "chaseEnemy2.X+random(-32, 32)",
								"y": "chaseEnemy2.Y+random(-32, 32)"
							}
						}
					],
					"sid": 172721042484369
				},
				{
					"eventType": "block",
					"conditions": [
						{
							"id": "has-los-to-object",
							"objectClass": "chaseEnemy2",
							"sid": 977493786700320,
							"behaviorType": "LineOfSight",
							"parameters": {
								"object": "TestPlayerC",
								"image-point": "0"
							}
						}
					],
					"actions": [
						{
							"id": "set-animation",
							"objectClass": "chaseEnemy2",
							"sid": 665980357831208,
							"parameters": {
								"animation": "\"HATE\"",
								"from": "beginning"
							}
						},
						{
							"id": "set-enabled",
							"objectClass": "chaseEnemy2",
							"sid": 865133328159770,
							"behaviorType": "Pathfinding",
							"parameters": {
								"set": "disabled"
							}
						},
						{
							"id": "move-to-object",
							"objectClass": "chaseEnemy2",
							"sid": 963082160821523,
							"behaviorType": "MoveTo",
							"parameters": {
								"object": "TestPlayerC",
								"image-point": "0",
								"mode": "direct"
							}
						},
						{
							"id": "wait",
							"objectClass": "System",
							"sid": 577819432829931,
							"disabled": true,
							"parameters": {
								"seconds": "2"
							}
						}
					],
					"sid": 663963207219467
				},
				{
					"eventType": "block",
					"conditions": [
						{
							"id": "has-los-to-object",
							"objectClass": "chaseEnemy2",
							"sid": 180316662345440,
							"behaviorType": "LineOfSight",
							"parameters": {
								"object": "TestPlayerC",
								"image-point": "0"
							},
							"isInverted": true
						}
					],
					"actions": [
						{
							"id": "wait",
							"objectClass": "System",
							"sid": 473842893468139,
							"parameters": {
								"seconds": "2"
							}
						},
						{
							"id": "set-animation",
							"objectClass": "chaseEnemy2",
							"sid": 883518229677887,
							"parameters": {
								"animation": "\"IDLE\"",
								"from": "beginning"
							}
						},
						{
							"id": "stop",
							"objectClass": "chaseEnemy2",
							"sid": 626806344738086,
							"behaviorType": "MoveTo"
						}
					],
					"sid": 376679712939832,
					"children": [
						{
							"eventType": "block",
							"conditions": [
								{
									"id": "every-x-seconds",
									"objectClass": "System",
									"sid": 896218592636955,
									"parameters": {
										"interval-seconds": "random(3,6)"
									}
								}
							],
							"actions": [
								{
									"id": "find-path",
									"objectClass": "chaseEnemy2",
									"sid": 259125769374923,
									"behaviorType": "Pathfinding",
									"parameters": {
										"x": "chaseEnemy2.X+random(-32, 32)",
										"y": "chaseEnemy2.Y+random(-32, 32)"
									}
								},
								{
									"id": "set-enabled",
									"objectClass": "chaseEnemy2",
									"sid": 617371743979119,
									"behaviorType": "Pathfinding",
									"parameters": {
										"set": "enabled"
									}
								}
							],
							"sid": 164830755183360
						}
					]
				},
				{
					"eventType": "block",
					"conditions": [
						{
							"id": "on-collision-with-another-object",
							"objectClass": "chaseEnemy2",
							"sid": 882770452157795,
							"parameters": {
								"object": "TestPlayerC"
							}
						}
					],
					"actions": [
						{
							"id": "subtract-from-eventvar",
							"objectClass": "System",
							"sid": 225001024165922,
							"parameters": {
								"variable": "HP",
								"value": "1"
							}
						},
						{
							"id": "flash",
							"objectClass": "TestPlayerC",
							"sid": 292977266897534,
							"behaviorType": "Flash",
							"parameters": {
								"on-time": "0.1",
								"off-time": "0.1",
								"duration": "1.0"
							}
						},
						{
							"id": "stop",
							"objectClass": "chaseEnemy2",
							"sid": 680257348731254,
							"behaviorType": "MoveTo"
						},
						{
							"id": "wait",
							"objectClass": "System",
							"sid": 452686200123814,
							"parameters": {
								"seconds": "2"
							}
						}
					],
					"sid": 823223517830397
				},
				{
					"eventType": "block",
					"conditions": [
						{
							"id": "on-collision-with-another-object",
							"objectClass": "chaseEnemy2",
							"sid": 413418664561221,
							"parameters": {
								"object": "TestPlayerC"
							}
						},
						{
							"id": "compare-eventvar",
							"objectClass": "System",
							"sid": 179273721998636,
							"parameters": {
								"variable": "HP",
								"comparison": 3,
								"value": "0"
							}
						}
					],
					"actions": [
						{
							"id": "restart-layout",
							"objectClass": "System",
							"sid": 116934507623978
						}
					],
					"sid": 609230067378841
				}
			],
			"sid": 393809270354236
		},
		{
			"eventType": "block",
			"conditions": [
				{
					"id": "every-tick",
					"objectClass": "System",
					"sid": 352534106340987
				},
				{
					"id": "compare-eventvar",
					"objectClass": "System",
					"sid": 816022846755944,
					"parameters": {
						"variable": "HP",
						"comparison": 0,
						"value": "3"
					}
				}
			],
			"actions": [
				{
					"id": "set-animation",
					"objectClass": "HP",
					"sid": 875812968080584,
					"parameters": {
						"animation": "\"HP3\"",
						"from": "beginning"
					}
				}
			],
			"sid": 581109042791978
		},
		{
			"eventType": "block",
			"conditions": [
				{
					"id": "every-tick",
					"objectClass": "System",
					"sid": 841204503912264
				},
				{
					"id": "compare-eventvar",
					"objectClass": "System",
					"sid": 291075162533519,
					"parameters": {
						"variable": "HP",
						"comparison": 0,
						"value": "2"
					}
				}
			],
			"actions": [
				{
					"id": "set-animation",
					"objectClass": "HP",
					"sid": 678506954398918,
					"parameters": {
						"animation": "\"HP2\"",
						"from": "beginning"
					}
				}
			],
			"sid": 289066680403974
		},
		{
			"eventType": "block",
			"conditions": [
				{
					"id": "every-tick",
					"objectClass": "System",
					"sid": 929807730244984
				},
				{
					"id": "compare-eventvar",
					"objectClass": "System",
					"sid": 160521752684951,
					"parameters": {
						"variable": "HP",
						"comparison": 0,
						"value": "1"
					}
				}
			],
			"actions": [
				{
					"id": "set-animation",
					"objectClass": "HP",
					"sid": 488418561121092,
					"parameters": {
						"animation": "\"HP1\"",
						"from": "beginning"
					}
				}
			],
			"sid": 241970074014656
		},
		{
			"eventType": "block",
			"conditions": [
				{
					"id": "every-tick",
					"objectClass": "System",
					"sid": 912238536364734
				},
				{
					"id": "compare-eventvar",
					"objectClass": "System",
					"sid": 937404534598427,
					"parameters": {
						"variable": "HP",
						"comparison": 3,
						"value": "0"
					}
				}
			],
			"actions": [
				{
					"id": "set-eventvar-value",
					"objectClass": "System",
					"sid": 537258622565650,
					"parameters": {
						"variable": "HP",
						"value": "3"
					}
				}
			],
			"sid": 359006675147105
		},
		{
			"eventType": "block",
			"conditions": [
				{
					"id": "on-collision-with-another-object",
					"objectClass": "TestPlayerC",
					"sid": 272118690276851,
					"parameters": {
						"object": "SteamEnd"
					}
				}
			],
			"actions": [
				{
					"id": "toggle-boolean-eventvar",
					"objectClass": "System",
					"sid": 579937912331125,
					"parameters": {
						"variable": "MineLevelComp"
					}
				},
				{
					"id": "go-to-layout",
					"objectClass": "System",
					"sid": 844118672318393,
					"parameters": {
						"layout": "LevelSelect"
					}
				}
			],
			"sid": 190893861386210
		},
		{
			"eventType": "block",
			"conditions": [
				{
					"id": "on-key-pressed",
					"objectClass": "key",
					"sid": 250411657892163,
					"parameters": {
						"key": 76
					}
				}
			],
			"actions": [
				{
					"id": "reset-global-variables",
					"objectClass": "System",
					"sid": 795708569800552
				},
				{
					"id": "go-to-layout",
					"objectClass": "System",
					"sid": 457174448291271,
					"parameters": {
						"layout": "LevelSelect"
					}
				}
			],
			"sid": 977086819484983
		}
	],
	"sid": 779865521013904
}