{
	"name": "CartScene",
	"layers": [
		{
			"name": "Layer 0",
			"overriden": 0,
			"subLayers": [],
			"instances": [],
			"sid": 697391856763432,
			"effectTypes": [],
			"isInitiallyVisible": true,
			"isInitiallyInteractive": true,
			"color": [
				1,
				1,
				1,
				1
			],
			"backgroundColor": [
				0.3686274509803922,
				0.3686274509803922,
				0.3686274509803922,
				1
			],
			"isTransparent": false,
			"parallaxX": 1,
			"parallaxY": 1,
			"scaleRate": 1,
			"forceOwnTexture": false,
			"renderingMode": "3d",
			"drawOrder": "z-order",
			"useRenderCells": false,
			"blendMode": "normal",
			"zElevation": 0,
			"global": false
		},
		{
			"name": "UI",
			"overriden": 0,
			"subLayers": [],
			"instances": [
				{
					"type": "MineCartWall",
					"properties": {
						"initially-visible": true,
						"initial-animation": "Default",
						"initial-frame": 0,
						"enable-collisions": true,
						"live-preview": false
					},
					"uid": 964,
					"instanceVariables": {},
					"behaviors": {},
					"world": {
						"x": 802,
						"y": 350,
						"width": 1616,
						"height": 736,
						"originX": 0.5,
						"originY": 0.5,
						"color": [
							1,
							1,
							1,
							1
						],
						"angle": 0,
						"zElevation": 0
					}
				}
			],
			"sid": 610249134567215,
			"effectTypes": [
				{
					"effectId": "waterbg",
					"name": "WaterBackground",
					"instance": {
						"isEnabled": false,
						"parameters": {
							"speed": 0.01,
							"x-speed": 0.02,
							"y-speed": 0.02,
							"intensity": 2,
							"frequency": 4,
							"angle": 7,
							"delta": 20,
							"reflectivity": 200,
							"emboss": 0.3
						}
					}
				}
			],
			"isInitiallyVisible": true,
			"isInitiallyInteractive": true,
			"color": [
				1,
				1,
				1,
				1
			],
			"backgroundColor": [
				0.3686274509803922,
				0.3686274509803922,
				0.3686274509803922,
				1
			],
			"isTransparent": true,
			"parallaxX": 1,
			"parallaxY": 1,
			"scaleRate": 1,
			"forceOwnTexture": false,
			"renderingMode": "3d",
			"drawOrder": "z-order",
			"useRenderCells": false,
			"blendMode": "normal",
			"zElevation": 0,
			"global": false
		},
		{
			"name": "Game",
			"overriden": 0,
			"subLayers": [],
			"instances": [
				{
					"type": "MCCartl",
					"properties": {
						"initially-visible": true,
						"initial-animation": "Default",
						"initial-frame": 0,
						"enable-collisions": true,
						"live-preview": false
					},
					"uid": 966,
					"instanceVariables": {},
					"behaviors": {
						"ScrollTo": {
							"properties": {
								"enabled": true
							}
						}
					},
					"world": {
						"x": 172,
						"y": 434,
						"width": 192,
						"height": 192,
						"originX": 0.5,
						"originY": 0.5,
						"color": [
							1,
							1,
							1,
							1
						],
						"angle": 0,
						"zElevation": 1
					}
				}
			],
			"sid": 269397777675071,
			"effectTypes": [],
			"isInitiallyVisible": true,
			"isInitiallyInteractive": true,
			"color": [
				1,
				1,
				1,
				1
			],
			"backgroundColor": [
				0.3686274509803922,
				0.3686274509803922,
				0.3686274509803922,
				1
			],
			"isTransparent": true,
			"parallaxX": 0,
			"parallaxY": 0,
			"scaleRate": 1,
			"forceOwnTexture": false,
			"renderingMode": "3d",
			"drawOrder": "z-order",
			"useRenderCells": false,
			"blendMode": "normal",
			"zElevation": 0,
			"global": false
		}
	],
	"sid": 154599703737378,
	"nonworld-instances": [],
	"effectTypes": [],
	"width": 1696,
	"height": 960,
	"unboundedScrolling": false,
	"vpX": 0.5,
	"vpY": 0.5,
	"projection": "perspective",
	"eventSheet": "CartScene"
}